LICENSE.md
MANIFEST.in
README.md
dynamic_extras_require.txt
dynamic_install_requires.txt
quicklib_incorporated.v2.5.zip
quicklib_setup_from_yml.py
epic/bitstore/__init__.py
epic/bitstore/__version__.py
epic/bitstore/aws.py
epic/bitstore/composite.py
epic/bitstore/exc.py
epic/bitstore/gcp.py
epic/bitstore/sha1.py
epic/bitstore/store.py
epic/bitstore/tests/__init__.py
epic/bitstore/tests/helpers.py
epic/bitstore/tests/test_aws.py
epic/bitstore/tests/test_gcp.py
epic/bitstore/tests/test_mocks.py
epic/bitstore/tests/test_sha1.py
epic_bitstore.egg-info/PKG-INFO
epic_bitstore.egg-info/SOURCES.txt
epic_bitstore.egg-info/dependency_links.txt
epic_bitstore.egg-info/requires.txt
epic_bitstore.egg-info/top_level.txt