Metadata-Version: 2.1
Name: epic-bitstore
Version: 1.0
Summary: Multi-tiered cloud-backed blob storage system
Home-page: https://github.com/Cybereason/epic-bitstore
Author: Yonatan Perry, Uri Sternfeld, Assaf Ben-David
License: MIT License
Classifier: Development Status :: 4 - Beta
Classifier: Intended Audience :: Developers
Classifier: Operating System :: POSIX :: Linux
Classifier: Operating System :: MacOS :: MacOS X
Classifier: Operating System :: Microsoft :: Windows
Classifier: Programming Language :: Python :: 3 :: Only
Classifier: Programming Language :: Python :: 3.10
Requires-Python: >=3.10
Provides-Extra: aws
Provides-Extra: gcp
License-File: LICENSE.md
